jupyter_code_executor_mcp_server/__init__.py
jupyter_code_executor_mcp_server/app.py
jupyter_code_executor_mcp_server/prompts.py
jupyter_code_executor_mcp_server-0.2.0.dist-info/WHEEL
jupyter_code_executor_mcp_server-0.2.0.dist-info/entry_points.txt
jupyter_code_executor_mcp_server-0.2.0.dist-info/METADATA
jupyter_code_executor_mcp_server-0.2.0.dist-info/RECORD
