Metadata-Version: 2.3
Name: jupyter-code-executor-mcp-server
Version: 0.2.0
Summary: Jupyter code executor mcp server
Keywords: ai,mcp,jupyter-mcp,code-executor,mcp-server,jupyter-code-executor-mcp-server
Author: curry tang
Author-email: curry tang <twn39@163.com>
Classifier: Intended Audience :: Developers
Classifier: License :: OSI Approved :: MIT License
Classifier: Programming Language :: Python :: 3
Classifier: Programming Language :: Python :: 3.11
Classifier: Programming Language :: Python :: 3.12
Classifier: Programming Language :: Python :: 3.13
Requires-Dist: autogen-core>=0.7.5
Requires-Dist: autogen-ext>=0.7.5
Requires-Dist: click>=8.3.1
Requires-Dist: jupyterlab>=4.5.0
Requires-Dist: matplotlib>=3.10.7
Requires-Dist: mcp[cli]>=1.23.1
Requires-Dist: pandas>=2.3.3
Requires-Dist: pip>=25.3
Requires-Dist: scikit-learn>=1.7.2
Requires-Dist: scipy>=1.16.3
Requires-Dist: seaborn>=0.13.2
Requires-Dist: statsmodels>=0.14.6
Requires-Dist: sympy>=1.14.0
Requires-Dist: uv>=0.9.16
Maintainer: curry tang
Maintainer-email: curry tang <twn39@163.com>
Requires-Python: >=3.11
